api/__init__.py
api/bq_api.py
api/gcs_api.py
database/__init__.py
database/bigquery/__init__.py
database/bigquery/bq_sql_parser.py
database/bigquery/bq_sql_parser_v2.py
database/bigquery/util.py
database/cloud_sql/__init__.py
database/cloud_sql/crud.py
database/cloud_storage/__init__.py
database/cloud_storage/util.py
gdrive_gcs_toolkit/__init__.py
gdrive_gcs_toolkit/cloud_storage/__init__.py
gdrive_gcs_toolkit/cloud_storage/util.py
gdrive_gcs_toolkit/google_shared_drive/__init__.py
gdrive_gcs_toolkit/google_shared_drive/util.py
model/__init__.py
model/file_info.py
shaku_database_latest-1.0.10.dist-info/LICENSE
shaku_database_latest-1.0.10.dist-info/METADATA
shaku_database_latest-1.0.10.dist-info/WHEEL
shaku_database_latest-1.0.10.dist-info/top_level.txt
shaku_database_latest-1.0.10.dist-info/RECORD
