Metadata-Version: 2.1
Name: shaku-database-latest
Version: 1.0.10
Summary: Shaku Database util
Home-page: https://gitlab.com/shaku-com/data-util
Author: shaku-developer
Author-email: laurencelin@shaku.com.tw
Classifier: Programming Language :: Python :: 3
Classifier: License :: OSI Approved :: MIT License
Classifier: Operating System :: OS Independent
Requires-Python: >=3.6
License-File: LICENSE
Requires-Dist: db-dtypes ==1.1.1
Requires-Dist: google-api-core ==2.11.0
Requires-Dist: google-auth ==2.18.0
Requires-Dist: google-cloud-bigquery ==3.10.0
Requires-Dist: google-cloud-core ==2.3.2
Requires-Dist: google-cloud-storage ==2.9.0
Requires-Dist: google-crc32c ==1.5.0
Requires-Dist: google-resumable-media ==2.5.0
Requires-Dist: googleapis-common-protos ==1.59.0
Requires-Dist: numpy ==1.24.3
Requires-Dist: openpyxl ==3.0.9
Requires-Dist: pandas ==2.0.1
Requires-Dist: pyarrow ==12.0.0
Requires-Dist: PyMySQL ==1.0.3
Requires-Dist: requests ==2.30.0
Requires-Dist: rsa ==4.9
Requires-Dist: setuptools ==67.7.2
Requires-Dist: six ==1.16.0
Requires-Dist: sqlalchemy ==2.0.13
Requires-Dist: chardet ==5.1.0
Requires-Dist: google-api-python-client ==2.90.0
Requires-Dist: google-auth-oauthlib ==1.0.0
Requires-Dist: google-auth-httplib2 ==0.1.0
Requires-Dist: pathlib ==1.0.1
Requires-Dist: google-cloud-bigquery-storage ==2.22.0
Requires-Dist: pandas-gbq ==0.19.2
Requires-Dist: pydata-google-auth ==1.8.2
Requires-Dist: Flask
Requires-Dist: Flask-RESTful
Provides-Extra: flask
Provides-Extra: flask-restful
Provides-Extra: pymysql
Requires-Dist: 1.0.3 ; extra == 'pymysql'
Provides-Extra: chardet
Requires-Dist: 5.1.0 ; extra == 'chardet'
Provides-Extra: db-dtypes
Requires-Dist: 1.1.1 ; extra == 'db-dtypes'
Provides-Extra: google-api-core
Requires-Dist: 2.11.0 ; extra == 'google-api-core'
Provides-Extra: google-api-python-client
Requires-Dist: 2.90.0 ; extra == 'google-api-python-client'
Provides-Extra: google-auth
Requires-Dist: 2.18.0 ; extra == 'google-auth'
Provides-Extra: google-auth-httplib2
Requires-Dist: 0.1.0 ; extra == 'google-auth-httplib2'
Provides-Extra: google-auth-oauthlib
Requires-Dist: 1.0.0 ; extra == 'google-auth-oauthlib'
Provides-Extra: google-cloud-bigquery
Requires-Dist: 3.10.0 ; extra == 'google-cloud-bigquery'
Provides-Extra: google-cloud-bigquery-storage
Requires-Dist: 2.22.0 ; extra == 'google-cloud-bigquery-storage'
Provides-Extra: google-cloud-core
Requires-Dist: 2.3.2 ; extra == 'google-cloud-core'
Provides-Extra: google-cloud-storage
Requires-Dist: 2.9.0 ; extra == 'google-cloud-storage'
Provides-Extra: google-crc32c
Requires-Dist: 1.5.0 ; extra == 'google-crc32c'
Provides-Extra: google-resumable-media
Requires-Dist: 2.5.0 ; extra == 'google-resumable-media'
Provides-Extra: googleapis-common-protos
Requires-Dist: 1.59.0 ; extra == 'googleapis-common-protos'
Provides-Extra: numpy
Requires-Dist: 1.24.3 ; extra == 'numpy'
Provides-Extra: openpyxl
Requires-Dist: 3.0.9 ; extra == 'openpyxl'
Provides-Extra: pandas
Requires-Dist: 2.0.1 ; extra == 'pandas'
Provides-Extra: pandas-gbq
Requires-Dist: 0.19.2 ; extra == 'pandas-gbq'
Provides-Extra: pathlib
Requires-Dist: 1.0.1 ; extra == 'pathlib'
Provides-Extra: pyarrow
Requires-Dist: 12.0.0 ; extra == 'pyarrow'
Provides-Extra: pydata-google-auth
Requires-Dist: 1.8.2 ; extra == 'pydata-google-auth'
Provides-Extra: requests
Requires-Dist: 2.30.0 ; extra == 'requests'
Provides-Extra: rsa
Requires-Dist: 4.9 ; extra == 'rsa'
Provides-Extra: setuptools
Requires-Dist: 67.7.2 ; extra == 'setuptools'
Provides-Extra: six
Requires-Dist: 1.16.0 ; extra == 'six'
Provides-Extra: sqlalchemy
Requires-Dist: 2.0.13 ; extra == 'sqlalchemy'
